submine/__init__.py
submine/api.py
submine/errors.py
submine/registry.py
submine/algorithms/__init__.py
submine/algorithms/base.py
submine/algorithms/gspan.py
submine/algorithms/gspan_cpp.cpython-39-x86_64-linux-gnu.so
submine/algorithms/sopagrami.py
submine/algorithms/sopagrami_cpp.cpython-39-x86_64-linux-gnu.so
submine/backends/__init__.py
submine/backends/gspan/CMakeLists.txt
submine/backends/gspan/dfs.cpp
submine/backends/gspan/graph.cpp
submine/backends/gspan/gspan.cpp
submine/backends/gspan/gspan.h
submine/backends/gspan/ismin.cpp
submine/backends/gspan/main.cpp
submine/backends/gspan/misc.cpp
submine/backends/gspan/python_bindings.cpp
submine/backends/sopagrami/cpp/CMakeLists.txt
submine/backends/sopagrami/cpp/include/alg.hpp
submine/backends/sopagrami/cpp/include/common/timer.hpp
submine/backends/sopagrami/cpp/src/alg.cpp
submine/backends/sopagrami/cpp/src/dump.cpp
submine/backends/sopagrami/cpp/src/main.cpp
submine/backends/sopagrami/cpp/src/python_bindings.cpp
submine/cli/__init__.py
submine/cli/main.py
submine/core/__init__.py
submine/core/graph.py
submine/core/result.py
submine/datasets/__init__.py
submine/datasets/loaders.py
submine/io/__init__.py
submine/io/common.py
submine/io/gexf.py
submine/io/gspan.py
submine/io/sopagrami.py
submine/io/transcode.py
submine/utils/__init__.py
submine/utils/checks.py
submine/utils/logging.py
submine-0.1.2.dist-info/METADATA
submine-0.1.2.dist-info/WHEEL
submine-0.1.2.dist-info/RECORD
submine-0.1.2.dist-info/licenses/LICENSE
