Metadata-Version: 2.2
Name: submine
Version: 0.1.2
Summary: Modular subgraph mining library with unified API
Keywords: graph-mining,subgraph-mining,gspan,frequent-subgraph-mining
Author: Ridwan Amure
License: MIT
Classifier: Programming Language :: Python :: 3
Classifier: Programming Language :: Python :: 3 :: Only
Classifier: License :: OSI Approved :: MIT License
Classifier: Operating System :: OS Independent
Project-URL: Homepage, https://github.com/instabaines/submine
Project-URL: Repository, https://github.com/instabaines/submine
Project-URL: Issues, https://github.com/instabaines/submine/issues
Requires-Python: >=3.9
Requires-Dist: networkx>=2.8
Provides-Extra: dev
Requires-Dist: pytest>=7; extra == "dev"
Requires-Dist: pytest-cov>=4; extra == "dev"
Requires-Dist: build>=1; extra == "dev"
Requires-Dist: twine>=5; extra == "dev"
Requires-Dist: ruff>=0.5; extra == "dev"
